general_config.py
general_config-0.0.1.dist-info/METADATA
general_config-0.0.1.dist-info/WHEEL
general_config-0.0.1.dist-info/top_level.txt
general_config-0.0.1.dist-info/RECORD
